lcu_connector/__init__.py
lcu_connector/connection.py
lcu_connector/connector.py
lcu_connector/exceptions.py
lcu_connector/riot.py
lcu_connector-1.0.2.dist-info/LICENSE
lcu_connector-1.0.2.dist-info/METADATA
lcu_connector-1.0.2.dist-info/WHEEL
lcu_connector-1.0.2.dist-info/dependency_links.txt
lcu_connector-1.0.2.dist-info/top_level.txt
lcu_connector-1.0.2.dist-info/RECORD
