Metadata-Version: 2.1
Name: lcu-connector
Version: 1.0.2
Summary: Easy-to-use wrapper for the League Client API.
Author: Gabriel Viana
Author-email: ssiriusbeck@gmail.com
Project-URL: Source, https://github.com/pySiriusDev/lcu-connector
Project-URL: Download, https://github.com/pySiriusDev/lcu-connector/releases
Project-URL: Instagram, https://instagram.com/biellviana
Project-URL: Twitter, https://twitter.com/_siriusbeck
Keywords: league client,league client api,league client api wrapper,api wrapperleague of legends,league of legends api,lcu-driver,lcu driver,lcu-connector,lcu connector
Classifier: Programming Language :: Python :: 3
Classifier: License :: OSI Approved :: MIT License
Classifier: Operating System :: OS Independent
Requires-Python: >=3.11
License-File: LICENSE
Requires-Dist: requests
Requires-Dist: psutil
